llama_index/__init__.py
llama_index/async_utils.py
llama_index/constants.py
llama_index/docstore.py
llama_index/docstore_v2.py
llama_index/img_utils.py
llama_index/schema.py
llama_index/utils.py
llama_index/composability/__init__.py
llama_index/composability/graph.py
llama_index/data_structs/__init__.py
llama_index/data_structs/data_structs.py
llama_index/data_structs/data_structs_v2.py
llama_index/data_structs/node_mapping.py
llama_index/data_structs/node_v2.py
llama_index/data_structs/struct_type.py
llama_index/data_structs/table.py
llama_index/data_structs/table_v2.py
llama_index/embeddings/__init__.py
llama_index/embeddings/base.py
llama_index/embeddings/langchain.py
llama_index/embeddings/openai.py
llama_index/embeddings/utils.py
llama_index/evaluation/__init__.py
llama_index/evaluation/base.py
llama_index/indices/__init__.py
llama_index/indices/base.py
llama_index/indices/prompt_helper.py
llama_index/indices/registry.py
llama_index/indices/service_context.py
llama_index/indices/utils.py
llama_index/indices/common/__init__.py
llama_index/indices/common/struct_store/__init__.py
llama_index/indices/common/struct_store/base.py
llama_index/indices/common/struct_store/schema.py
llama_index/indices/common/struct_store/sql.py
llama_index/indices/common/tree/__init__.py
llama_index/indices/common/tree/base.py
llama_index/indices/composability/__init__.py
llama_index/indices/composability/graph.py
llama_index/indices/empty/__init__.py
llama_index/indices/empty/base.py
llama_index/indices/keyword_table/__init__.py
llama_index/indices/keyword_table/base.py
llama_index/indices/keyword_table/rake_base.py
llama_index/indices/keyword_table/simple_base.py
llama_index/indices/keyword_table/utils.py
llama_index/indices/knowledge_graph/__init__.py
llama_index/indices/knowledge_graph/base.py
llama_index/indices/list/__init__.py
llama_index/indices/list/base.py
llama_index/indices/postprocessor/__init__.py
llama_index/indices/postprocessor/node.py
llama_index_sl-0.0.1.dist-info/METADATA
llama_index_sl-0.0.1.dist-info/WHEEL
llama_index_sl-0.0.1.dist-info/top_level.txt
llama_index_sl-0.0.1.dist-info/RECORD
