Metadata-Version: 2.1
Name: llama-index-sl
Version: 0.0.1
Summary: llama_index edited for unicode support
Home-page: UNKNOWN
Author: sl
License: UNKNOWN
Keywords: python
Platform: UNKNOWN
Classifier: Development Status :: 1 - Planning
Classifier: Intended Audience :: Developers
Classifier: Programming Language :: Python :: 3
Classifier: Operating System :: Unix
Classifier: Operating System :: MacOS :: MacOS X
Classifier: Operating System :: Microsoft :: Windows
Requires-Dist: pdfminer
